<?xml version='1.0' encoding='utf-8'?>
<items>
  <item id="1158785574" name="Bracelet usé"/>
  <item id="3681894277" name="Bracelet en toc"/>
  <item id="3692624796" name="Bracelet rocker"/>
  <item id="2893156115" name="Bracelet de force"/>
  <item id="2870987530" name="Bracelet brute"/>
  <item id="1020072578" name="Bracelet majest."/>
  <item id="897277609" name="Bracelet solaire"/>
  <item id="1271538196" name="Bracelet de comète"/>
  <item id="1115450943" name="Bracelet obscur"/>
  <item id="722316273" name="Bracelet légend."/>
  <item id="1154727953" name="Anneau rouillé"/>
  <item id="3669448114" name="Anneau horrible"/>
  <item id="3722088875" name="Bague mimi"/>
  <item id="2914018596" name="Anneau arc-en-ciel"/>
  <item id="2866651453" name="Anneau illusion"/>
  <item id="1024424117" name="Anneau féérique"/>
  <item id="884552862" name="Anneau lunaire"/>
  <item id="1242056739" name="Anneau du destin"/>
  <item id="1136526344" name="Anneau obscur"/>
  <item id="718258630" name="Anneau légendaire"/>
  <item id="1184202312" name="Amul. vieillotte"/>
  <item id="3639733227" name="Amulette antique"/>
  <item id="3751555058" name="Amulette runique"/>
  <item id="2952190845" name="Amul. protectrice"/>
  <item id="2828738404" name="Amulette armure"/>
  <item id="1061799660" name="Amul. de chance"/>
  <item id="922716871" name="Amulette céleste"/>
  <item id="1213134458" name="Amulette de terre"/>
  <item id="1106819665" name="Amul. obscure"/>
  <item id="680099743" name="Amul. légendaire"/>
  <item id="1196889215" name="Badge simple"/>
  <item id="3644031452" name="Badge noir"/>
  <item id="3730720197" name="Badge brillant"/>
  <item id="2922688842" name="Badge mignon"/>
  <item id="2841212243" name="Badge d'Hermès"/>
  <item id="1049341147" name="Badge de l'aurore"/>
  <item id="926802160" name="Badge étoiles"/>
  <item id="1233951821" name="Badge de foudre"/>
  <item id="1077596262" name="Badge obscur"/>
  <item id="692786600" name="Badge légendaire"/>
  <item id="1108869882" name="Cigatana"/>
  <item id="3675345728" name="Clochette force"/>
  <item id="2887148502" name="Cloch. charme"/>
  <item id="846394997" name="Cloch. vigueur"/>
  <item id="1165346531" name="Cloch. vitesse"/>
  <item id="3699152729" name="Gour. sans fond"/>
  <item id="2877007823" name="Éventail de tengu"/>
  <item id="1002748510" name="Manteau d'allégr."/>
  <item id="1287883464" name="Batte cloutée"/>
  <item id="1550776226" name="Baguettes de tamb."/>
  <item id="3311904280" name="Robovitamine E"/>
  <item id="2992674446" name="Poignet d'Antonic"/>
  <item id="585075487" name="Grelot du souvenir"/>
  <item id="3037549207" name="Bracelet de farceur"/>
  <item id="728352564" name="Bracelet de bouffi"/>
  <item id="738460461" name="Laméliore"/>
  <item id="1526936507" name="Grigrififi"/>
  <item id="3255460353" name="Réflector"/>
  <item id="1440267145" name="Boule du paradis"/>
  <item id="1138387149" name="Lettre funeste"/>
  <item id="3671275895" name="Sabre maudit"/>
  <item id="2916354529" name="Bâton maudit"/>
  <item id="867212354" name="Bouclier maudit"/>
  <item id="1152888020" name="Robe maudite"/>
  <item id="1100797588" name="Ceinture retenue"/>
  <item id="2945628088" name="Coiffe de singe"/>
  <item id="4256025923" name="Méd. de général"/>
  <item id="1688509689" name="Méd. de colonel"/>
  <item id="329493615" name="Méd. lt.-colonel"/>
  <item id="2378643916" name="Méd. de commdt"/>
  <item id="4206889306" name="Méd. capitaine"/>
  <item id="1674139872" name="Méd. lieutenant"/>
  <item id="349071478" name="Méd. d'adjudant"/>
  <item id="2222028263" name="Méd. de caporal"/>
</items>
